seasave_data_conversion/__init__.py
seasave_data_conversion/cnv_converter.py
seasave_data_conversion-0.0.1.dist-info/LICENSE
seasave_data_conversion-0.0.1.dist-info/WHEEL
seasave_data_conversion-0.0.1.dist-info/METADATA
seasave_data_conversion-0.0.1.dist-info/RECORD
