Metadata-Version: 2.1
Name: seasave_data_conversion
Version: 0.0.1
Summary: Converts ctd data (*.cnv) to csv and txt file. Also structures data to Pangaea format
Author-email: Raja sekar <shanthakumar.rajasekar@gmail.com>
Requires-Python: >=3.6
Classifier: License :: OSI Approved :: MIT License
